hardness/__init__.py
hardness/database.py
hardness/models.py
hardness/postproc.py
hardness/templates/models/indentation_2D/conical_indenter_mesh_2D.geo
hardness/templates/models/indentation_2D/indentation_2D.inp
hardness/templates/models/indentation_2D/indentation_2D_abqpostproc.py
hardness/templates/models/indentation_2D/indentation_2D_pypostproc.py
hardness/templates/models/indentation_2D/indentation_fibre_mesh_2D.geo
hardness/templates/models/indentation_2D/indentation_mesh_2D.geo
hardness/templates/models/indentation_2D/spheroconical_indenter_mesh_2D.geo
hardness/templates/models/indentation_2D/steps/indentation_2D_step_disp_control_adaptative.inp
hardness/templates/models/indentation_2D/steps/indentation_2D_step_disp_control_fixed.inp
hardness/templates/models/indentation_2D/steps/indentation_2D_step_load_control_adaptative.inp
hardness/templates/models/indentation_2D/steps/indentation_2D_step_load_control_fixed.inp
hardness-0.3.dist-info/DESCRIPTION.rst
hardness-0.3.dist-info/METADATA
hardness-0.3.dist-info/RECORD
hardness-0.3.dist-info/WHEEL
hardness-0.3.dist-info/metadata.json
hardness-0.3.dist-info/top_level.txt
