Metadata-Version: 2.0
Name: hardness
Version: 0.3
Summary: Python Indentation Toolbox
Home-page: https://github.com/lcharleux/hardness
Author: Ludovic Charleux
Author-email: ludovic.charleux@univ-smb.fr
License: GPL v3
Platform: UNKNOWN
Requires-Dist: argiope
Requires-Dist: jupyter
Requires-Dist: matplotlib
Requires-Dist: nbconvert
Requires-Dist: numpy
Requires-Dist: pandas
Requires-Dist: scipy
